vcr_stub_server/__init__.py
vcr_stub_server/__main__.py
vcr_stub_server/cassettes/__init__.py
vcr_stub_server/cassettes/base_vcr_cassette.py
vcr_stub_server/cassettes/vcrpy_cassette.py
vcr_stub_server/stub_server_handler.py
vcr_stub_server-0.1.4.dist-info/entry_points.txt
vcr_stub_server-0.1.4.dist-info/LICENSE
vcr_stub_server-0.1.4.dist-info/WHEEL
vcr_stub_server-0.1.4.dist-info/METADATA
vcr_stub_server-0.1.4.dist-info/RECORD
