Metadata-Version: 2.1
Name: vcr-stub-server
Version: 0.1.4
Summary: Standalone stub server for replaying VCR cassettes
Home-page: https://github.com/thatguysimon/vcr-stub-server
License: MIT
Keywords: vcr,vcrpy,stub,standalone,server
Author: Simon Nizov
Author-email: simon.nizov@gmail.com
Requires-Python: >=3.6,<4.0
Classifier: License :: OSI Approved :: MIT License
Classifier: Programming Language :: Python :: 3
Classifier: Programming Language :: Python :: 3.6
Classifier: Programming Language :: Python :: 3.7
Classifier: Programming Language :: Python :: 3.8
Requires-Dist: vcrpy (>=4.0.2,<5.0.0)
Project-URL: Repository, https://github.com/thatguysimon/vcr-stub-server
